napari_guitils/__init__.py
napari_guitils/gui_structures.py
napari_guitils/gui_widgets.py
napari_guitils-0.1.0.dist-info/METADATA
napari_guitils-0.1.0.dist-info/WHEEL
napari_guitils-0.1.0.dist-info/licenses/LICENSE
napari_guitils-0.1.0.dist-info/RECORD
