Metadata-Version: 2.1
Name: napari-guitils
Version: 0.1.0
Summary: Utils to create napari guis
Project-URL: homepage, https://github.com/guiwitz/napari-guitils
Project-URL: repository, https://github.com/guiwitz/napari-guitils
Author-email: Guillaume Witz <guillaume.witz@unibe.ch>
License: BSD 3-Clause License
License-File: LICENSE
Requires-Python: >=3.8
Requires-Dist: natsort
Requires-Dist: qtpy
Provides-Extra: test
Requires-Dist: napari; extra == 'test'
Requires-Dist: pyqt5; extra == 'test'
Requires-Dist: pytest; extra == 'test'
Requires-Dist: pytest-cov; extra == 'test'
Requires-Dist: pytest-qt; extra == 'test'
Requires-Dist: tox; extra == 'test'
